wagtail_reoako/__init__.py
wagtail_reoako/apps.py
wagtail_reoako/reoako_client.py
wagtail_reoako/static_src/wagtail_reoako/js/DraftUtils.js
wagtail_reoako/static_src/wagtail_reoako/js/reoako.js
wagtail_reoako/templates/wagtail_reoako/_ajax_results.html
wagtail_reoako/templates/wagtail_reoako/_results.html
wagtail_reoako/templates/wagtail_reoako/reoako.html
wagtail_reoako/templates/wagtail_reoako/reoako_icon.svg
wagtail_reoako/urls.py
wagtail_reoako/views.py
wagtail_reoako/wagtail_hooks.py
wagtail_reoako-2.1.2.dist-info/LICENSE
wagtail_reoako-2.1.2.dist-info/METADATA
wagtail_reoako-2.1.2.dist-info/WHEEL
wagtail_reoako-2.1.2.dist-info/RECORD
