Metadata-Version: 2.1
Name: wagtail-reoako
Version: 2.1.2
Summary: Wagtail Reoako module.
Author: Octave
Author-email: support@octave.nz
Requires-Python: >=3.10,<3.11
Classifier: Programming Language :: Python :: 3
Classifier: Programming Language :: Python :: 3.10
Requires-Dist: Django (>=4.2,<4.3)
Requires-Dist: django-extensions (>=3.1,<4.0)
Requires-Dist: psycopg2-binary (>=2.8,<2.9)
Requires-Dist: wagtail (>=5.2,<5.3)
